rust_regex-0.1.0_alpha1.dist-info/METADATA
rust_regex-0.1.0_alpha1.dist-info/WHEEL
rust_regex-0.1.0_alpha1.dist-info/license_files/LICENSE
rust_regex/__init__.py
rust_regex/__init__.pyi
rust_regex/py.typed
rust_regex/rust_regex.abi3.so
rust_regex-0.1.0_alpha1.dist-info/RECORD
