Metadata-Version: 2.1
Name: rust_regex
Version: 0.1.0_alpha1
Classifier: Development Status :: 3 - Alpha
Classifier: License :: OSI Approved :: GNU Lesser General Public License v2 or later (LGPLv2+)
Classifier: Operating System :: POSIX :: Linux
Classifier: Operating System :: MacOS
Classifier: Operating System :: Microsoft :: Windows
Classifier: Programming Language :: Rust
Classifier: Programming Language :: Python :: Implementation :: CPython
Classifier: Programming Language :: Python :: Implementation :: PyPy
Classifier: Programming Language :: Python :: 3.7
Classifier: Programming Language :: Python :: 3.8
Classifier: Programming Language :: Python :: 3.9
Classifier: Programming Language :: Python :: 3.10
Classifier: Programming Language :: Python :: 3.11
Classifier: Programming Language :: Python :: 3 :: Only
License-File: LICENSE
Summary: Python bindings for the Rust regex crate
Author: MiguelX413
Author-email: lbpgaming27@gmail.com
Requires-Python: >=3.7
Project-URL: GitLab, https://gitlab.com/MiguelX413/rust_regex
Project-URL: GitHub, https://github.com/MiguelX413/rust_regex
